victron_vrm/__init__.py
victron_vrm/client.py
victron_vrm/consts.py
victron_vrm/exceptions.py
victron_vrm/mqtt.py
victron_vrm/utils.py
victron_vrm/models/__init__.py
victron_vrm/models/aggregations.py
victron_vrm/models/alarm.py
victron_vrm/models/attributes.py
victron_vrm/models/auth.py
victron_vrm/models/base.py
victron_vrm/models/device.py
victron_vrm/models/diagnostics.py
victron_vrm/models/measurement.py
victron_vrm/models/site.py
victron_vrm/models/system_overview.py
victron_vrm/models/user.py
victron_vrm/modules/__init__.py
victron_vrm/modules/_base.py
victron_vrm/modules/installations.py
victron_vrm/modules/users.py
victron_vrm-0.1.11.dist-info/METADATA
victron_vrm-0.1.11.dist-info/WHEEL
victron_vrm-0.1.11.dist-info/licenses/LICENSE
victron_vrm-0.1.11.dist-info/RECORD
