Metadata-Version: 2.4
Name: victron-vrm
Version: 0.1.11
Summary: Async Python client for the Victron Energy VRM API and MQTT client for VRM
Project-URL: Homepage, https://github.com/KSoft-Si/vrm-client
Project-URL: Bug Tracker, https://github.com/KSoft-Si/vrm-client/issues
Author: AndyTempel
Author-email: "KSoft.TECH" <oss@ksoft.tech>
License: MIT
License-File: LICENSE
Keywords: api,async,client,home-assistant,victron,vrm
Classifier: Development Status :: 4 - Beta
Classifier: Intended Audience :: Developers
Classifier: License :: OSI Approved :: MIT License
Classifier: Programming Language :: Python :: 3
Classifier: Programming Language :: Python :: 3.11
Classifier: Programming Language :: Python :: 3.12
Classifier: Programming Language :: Python :: 3.13
Classifier: Topic :: Home Automation
Classifier: Topic :: Software Development :: Libraries
Requires-Python: >=3.11
Requires-Dist: aiohttp[speedups]>=3.8.0
Requires-Dist: pydantic>=2.0.0
Requires-Dist: pytz>=2025.2
Requires-Dist: victron-mqtt==2026.1.4
Provides-Extra: dev
Requires-Dist: black>=23.0.0; extra == 'dev'
Requires-Dist: isort>=5.0.0; extra == 'dev'
Requires-Dist: mypy>=1.0.0; extra == 'dev'
Requires-Dist: python-dotenv>=1.0.0; extra == 'dev'
Requires-Dist: ruff>=0.0.0; extra == 'dev'
Provides-Extra: test
Requires-Dist: pytest-asyncio>=0.20.0; extra == 'test'
Requires-Dist: pytest-cov>=4.0.0; extra == 'test'
Requires-Dist: pytest>=7.0.0; extra == 'test'
